GitResultsManager/GitResultsManager.py
GitResultsManager/__init__.py
GitResultsManager/resman_script.py
GitResultsManager/resman_td_script.py
gitresultsmanager-0.5.0.data/scripts/git-recreate
gitresultsmanager-0.5.0.data/scripts/rmtd
gitresultsmanager-0.5.0.dist-info/licenses/LICENSE.txt
gitresultsmanager-0.5.0.dist-info/METADATA
gitresultsmanager-0.5.0.dist-info/WHEEL
gitresultsmanager-0.5.0.dist-info/entry_points.txt
gitresultsmanager-0.5.0.dist-info/top_level.txt
gitresultsmanager-0.5.0.dist-info/RECORD
