Metadata-Version: 2.4
Name: GitResultsManager
Version: 0.5.0
Summary: The GitResultsManager Python module and scripts (resman) for keeping track of research results using Git.
Author-email: Jason Yosinski <git_results_manager.jyo@0sg.net>
License-Expression: GPL-3.0-or-later
Project-URL: Homepage, https://github.com/yosinski/GitResultsManager
Project-URL: Bug Tracker, https://github.com/yosinski/GitResultsManager/issues
Requires-Python: >=3.8
License-File: LICENSE.txt
Dynamic: license-file
